trainscanner/__init__.py
trainscanner/converter/__init__.py
trainscanner/converter/movie.py
trainscanner/converter/rect.py
trainscanner/decorators.py
trainscanner/gui/__init__.py
trainscanner/gui/converter.py
trainscanner/gui/pass1.py
trainscanner/gui/preprocess.py
trainscanner/gui/shake_reduction.py
trainscanner/gui/stitch.py
trainscanner/gui/trainscanner.py
trainscanner/gui/tspos_plotter.py
trainscanner/i18n/Makefile
trainscanner/i18n/__init__.py
trainscanner/i18n/extract.py
trainscanner/i18n/trainscanner_fr.ts
trainscanner/i18n/trainscanner_ja.ts
trainscanner/image/__init__.py
trainscanner/image/canvas.py
trainscanner/image/scaledcanvas.py
trainscanner/memory_monitor.py
trainscanner/pass1.py
trainscanner/shake_reduction.py
trainscanner/stitch.py
trainscanner/tspos_plot.py
trainscanner/video/__init__.py
trainscanner/video/ffmpeg.py
trainscanner/video/image_dir.py
trainscanner/video/video_cv2.py
trainscanner/widget/__init__.py
trainscanner/widget/imagebar.py
trainscanner/widget/imageselector2.py
trainscanner/widget/options.py
trainscanner/widget/perspective.py
trainscanner/widget/qfloatslider.py
trainscanner/widget/qlogslider.py
trainscanner/widget/qrangeslider.py
trainscanner/widget/qvalueslider.py
trainscanner-1.0.5.dist-info/METADATA
trainscanner-1.0.5.dist-info/WHEEL
trainscanner-1.0.5.dist-info/entry_points.txt
trainscanner-1.0.5.dist-info/RECORD
