Metadata-Version: 2.3
Name: trainscanner
Version: 1.0.5
Summary: 
License: MIT
Author: vitroid
Author-email: vitroid@gmail.com
Requires-Python: >=3.11,<4.0
Classifier: License :: OSI Approved :: MIT License
Classifier: Programming Language :: Python :: 3
Classifier: Programming Language :: Python :: 3.11
Classifier: Programming Language :: Python :: 3.12
Classifier: Programming Language :: Python :: 3.13
Requires-Dist: deprecation (>=2.1.0,<3.0.0)
Requires-Dist: imagecodecs (>=2025.8.2,<2026.0.0)
Requires-Dist: matplotlib (>=3.10.3,<4.0.0)
Requires-Dist: opencv-python (>=4.12.0.88,<5.0.0.0)
Requires-Dist: psutil (>=7.0.0,<8.0.0)
Requires-Dist: pyperbox (>=0.1.1,<0.2.0)
Requires-Dist: pyqt6 (>=6.8.0,<7.0.0)
Requires-Dist: rasterio (>=1.4.3,<2.0.0)
Requires-Dist: scipy (>=1.16.0,<2.0.0)
Requires-Dist: tiffeditor (>=0.4.0,<0.5.0)
Project-URL: Homepage, https://github.com/vitroid/trainscanner
